caqtus_parsing/_parser.py
caqtus_parsing/__init__.py
caqtus_parsing/_binding.abi3.so
caqtus_parsing/binding.c
caqtus_parsing/py.typed
caqtus_parsing/nodes/_nodes.py
caqtus_parsing/nodes/__init__.py
caqtus_parsing-0.4.0.dist-info/top_level.txt
caqtus_parsing-0.4.0.dist-info/RECORD
caqtus_parsing-0.4.0.dist-info/METADATA
caqtus_parsing-0.4.0.dist-info/WHEEL
